{"card_name": "Ardor, Forefront of Freedom", "color": "R", "rarity": "rare", "type": "Legendary Creature \u2013 Human Soldier", "number": 145, "color_identity": "R", "cost": "{2}{R}{R}", "rules_text": "Menace\nCreature tokens you control get +1/+1, have haste, and must attack each combat if able.\nAt the beginning of combat on your turn, create a 1/1 red Soldier creature token.", "pt": "3/3", "special_text": "", "shape": "normal", "set": "CYB", "loyalty": "", "notes": "!canoncard Brudiclad, Telchor Engineer"}