{"card_name": "Alien Pledge", "color": "", "rarity": "rare", "type": "Sorcery", "number": 1, "color_identity": "WB", "cost": "{1}{C}", "rules_text": "Create a token that\u2019s a copy of target creature you control, except it\u2019s a 1/1. When you do, pay for and choose any number.\n+{C} \u2013 That token becomes a copy of a different target creature.\n+{W} \u2013 You gain life equal to the number of creatures you control.\n+{B} \u2013 Each player sacrifices a creature.", "pt": "", "special_text": "", "shape": "normal", "set": "CYB", "loyalty": "", "notes": "!canoncard Witherbloom Command"}