{"card_name": "Callisto, the Teqiarch", "color": "U", "rarity": "rare", "type": "Legendary Creature \u2013 Human Wizard", "number": 73, "color_identity": "U", "cost": "{2}{U}", "rules_text": "At the beginning of your upkeep, exile the top card of target opponent\u2019s library. You may play that card for as long as it remains exiled, and mana of any type can be spent to cast it.\nSpells you cast and don\u2019t own cost {1} less to cast.", "pt": "2/4", "special_text": "", "shape": "normal", "set": "CYB", "loyalty": "", "notes": "!canoncard Brainstealer Dragon"}